mastui/__init__.py
mastui/app.css
mastui/app.py
mastui/autocomplete.py
mastui/cache.py
mastui/config.py
mastui/config_screen.py
mastui/confirm_dialog.py
mastui/conversation_screen.py
mastui/edit_post_screen.py
mastui/hashtag_timeline.py
mastui/header.py
mastui/help_screen.py
mastui/image.py
mastui/key_input.py
mastui/keybind_manager.py
mastui/keybind_screen.py
mastui/languages.py
mastui/log_viewer_screen.py
mastui/logging_config.py
mastui/login.py
mastui/logo.py
mastui/mastodon_api.py
mastui/messages.py
mastui/post.py
mastui/profile.py
mastui/profile_manager.py
mastui/profile_selection.py
mastui/reply.py
mastui/retro.py
mastui/search_screen.py
mastui/splash.py
mastui/theme_manager.py
mastui/thread.py
mastui/timeline.py
mastui/timeline_content.py
mastui/update_dialog.py
mastui/url_selector.py
mastui/utils.py
mastui/version_check.py
mastui/widgets.py
mastui-1.7.0.dist-info/LICENSE
mastui-1.7.0.dist-info/METADATA
mastui-1.7.0.dist-info/WHEEL
mastui-1.7.0.dist-info/entry_points.txt
mastui-1.7.0.dist-info/RECORD
