Metadata-Version: 2.1
Name: mastui
Version: 1.7.0
Summary: A Mastodon TUI client.
Author: Kim Schulz
Requires-Python: >=3.9,<4.0
Classifier: Programming Language :: Python :: 3
Classifier: Programming Language :: Python :: 3.9
Classifier: Programming Language :: Python :: 3.10
Classifier: Programming Language :: Python :: 3.11
Classifier: Programming Language :: Python :: 3.12
Requires-Dist: Pillow (>=10.3.0,<11.0.0)
Requires-Dist: beautifulsoup4 (>=4.13.4,<5.0.0)
Requires-Dist: clipman (>=3.3.3,<4.0.0)
Requires-Dist: html2text (>=2024.2.26,<2025.0.0)
Requires-Dist: httpx (>=0.27.0,<0.28.0)
Requires-Dist: mastodon-py (>=2.0.1,<3.0.0)
Requires-Dist: python-dateutil (>=2.9.0,<3.0.0)
Requires-Dist: python-dotenv (>=1.0.1,<2.0.0)
Requires-Dist: requests (>=2.32.4,<3.0.0)
Requires-Dist: textual (>=0.59.0)
Requires-Dist: textual-image (>=0.8.3,<0.9.0)
Requires-Dist: toml (>=0.10.2,<0.11.0)
